kittyself/__init__.py
kittyself/core.py
kittyself-0.1.0.dist-info/METADATA
kittyself-0.1.0.dist-info/WHEEL
kittyself-0.1.0.dist-info/top_level.txt
kittyself-0.1.0.dist-info/RECORD
