Metadata-Version: 2.4
Name: kittyself
Version: 0.1.0
Summary: a lightweight websocket bot helper for kitty.casino
Author: lumi
License: MIT
Requires-Python: >=3.8
Requires-Dist: websockets>=12.0
